[{"name":"sessionid","value":"47200197285%3ApBN6mFSKxvnind%3A5","domain":".instagram.com","path":"/","expires":1650251439.993891,"size":41,"httpOnly":true,"secure":true,"session":false,"sameParty":false,"sourceScheme":"Secure","sourcePort":443},{"name":"rur","value":"FRC","domain":".instagram.com","path":"/","expires":-1,"size":6,"httpOnly":true,"secure":true,"session":true,"sameParty":false,"sourceScheme":"Secure","sourcePort":443},{"name":"csrftoken","value":"x9Z6KSYduzHPxKtBIKQJYEHMRKLW1Wux","domain":".instagram.com","path":"/","expires":1650165041.151741,"size":41,"httpOnly":false,"secure":true,"session":false,"sameParty":false,"sourceScheme":"Secure","sourcePort":443},{"name":"ig_nrcb","value":"1","domain":".instagram.com","path":"/","expires":1650251437.177157,"size":8,"httpOnly":false,"secure":true,"session":false,"sameParty":false,"sourceScheme":"Secure","sourcePort":443},{"name":"ds_user_id","value":"47200197285","domain":".instagram.com","path":"/","expires":1626491441.151848,"size":21,"httpOnly":false,"secure":true,"session":false,"sameParty":false,"sourceScheme":"Secure","sourcePort":443},{"name":"ig_did","value":"8801C5C5-8FD3-4D1F-8FF2-CE04739ED6CD","domain":".instagram.com","path":"/","expires":1681787437.177123,"size":42,"httpOnly":true,"secure":true,"session":false,"sameParty":false,"sourceScheme":"Secure","sourcePort":443},{"name":"mid","value":"YHujKwALAAENPkfoNdH_hONqTYSu","domain":".instagram.com","path":"/","expires":1681787437.177089,"size":31,"httpOnly":false,"secure":true,"session":false,"sameParty":false,"sourceScheme":"Secure","sourcePort":443}]